humancrypto/VERSION
humancrypto/__init__.py
humancrypto/cli.py
humancrypto/current.py
humancrypto/error.py
humancrypto/pki.py
humancrypto/pwutil.py
humancrypto/randomutil.py
humancrypto/y2016.py
humancrypto/y44bc.py
humancrypto/yearutil.py
humancrypto-0.5.0.data/scripts/humancrypto
humancrypto-0.5.0.dist-info/DESCRIPTION.rst
humancrypto-0.5.0.dist-info/METADATA
humancrypto-0.5.0.dist-info/RECORD
humancrypto-0.5.0.dist-info/WHEEL
humancrypto-0.5.0.dist-info/metadata.json
humancrypto-0.5.0.dist-info/top_level.txt
