Metadata-Version: 2.0
Name: humancrypto
Version: 0.5.0
Summary: Cryptography for Humans
Home-page: https://github.com/iffy/humancrypto
Author: Matt Haggard
Author-email: haggardii@gmail.com
License: UNKNOWN
Platform: UNKNOWN
Requires-Dist: argon2-cffi (==16.1.0)
Requires-Dist: cryptography
Requires-Dist: six
